mapdispatch/__init__.py
mapdispatch/multimethod.py
mapdispatch/examples/zoo.py
mapdispatch-0.1.0.dist-info/licenses/LICENSE
mapdispatch-0.1.0.dist-info/METADATA
mapdispatch-0.1.0.dist-info/WHEEL
mapdispatch-0.1.0.dist-info/entry_points.txt
mapdispatch-0.1.0.dist-info/top_level.txt
mapdispatch-0.1.0.dist-info/RECORD
