Metadata-Version: 2.4
Name: mapdispatch
Version: 0.1.0
Summary: Clojure-style classless map-based multimethods and dispatch system for Python
Author-email: Gwang-Jin Kim <gwang.jin.kim.phd@gmail.com>
License-Expression: MIT
Project-URL: Homepage, https://github.com/gwangjinkim/mapdispatch
Requires-Python: >=3.7
License-File: LICENSE
Dynamic: license-file
